{"about_about.md":"b6c2ece8","about_team.md":"081acd85","blog_01-jeecg-menu-config.md":"4efad6d5","blog_index.md":"326866e9","code_index.md":"a4257490","index.md":"acf8b281","mdn_browser_01-浏览器手册_01-开发环境搭建.md":"d4bea46c","mdn_browser_index.md":"8137df4a","mdn_es6_01-es6手册_01-开发环境搭建.md":"3ddef858","mdn_es6_index.md":"4fc182c0","mdn_typescript_01-typescript手册_01-开发环境搭建.md":"897c97ae","mdn_web_javascript_01-javascript手册_01-开发环境搭建.md":"551f9de8","mdn_vue_01-vue手册_01-开发环境搭建.md":"4cdb0415","mdn_vue_index.md":"a5bc1d38","mdn_web_css_01-css手册_01-开发环境搭建.md":"ac17d2df","mdn_web_css_index.md":"c922f1e2","mdn_web_html_01-html5-canvas.md":"8f322f6a","mdn_web_index.md":"7ee0a3b5","about_markdown.md":"05673f05","mdn_web_jquery_index.md":"50c4d128","mdn_web_javascript_index.md":"7752e20b","mdn_web_jquery_01-jquery手册_01-开发环境搭建.md":"9a17f669","nav_index.md":"a4b303de","mdn_typescript_index.md":"0ba099e7"}
